LICENSE
MANIFEST.in
README.rst
setup.py
django_verification_token.egg-info/PKG-INFO
django_verification_token.egg-info/SOURCES.txt
django_verification_token.egg-info/dependency_links.txt
django_verification_token.egg-info/not-zip-safe
django_verification_token.egg-info/requires.txt
django_verification_token.egg-info/top_level.txt
example/__init__.py
example/manage.py
example/dj/__init__.py
example/dj/urls.py
example/dj/wsgi.py
example/dj/apps/__init__.py
example/dj/apps/app/__init__.py
example/dj/apps/app/models.py
example/dj/apps/app/tests/__init__.py
example/dj/apps/app/tests/base.py
example/dj/apps/app/tests/commands.py
example/dj/apps/app/tests/models.py
example/dj/settings/__init__.py
example/dj/settings/base.py
example/dj/settings/settings.py
verification_token/__init__.py
verification_token/config.py
verification_token/generators.py
verification_token/models.py
verification_token/version.py
verification_token/management/__init__.py
verification_token/management/commands/__init__.py
verification_token/management/commands/clean_verification_tokens.py
verification_token/migrations/0001_initial.py
verification_token/migrations/0002.py
verification_token/migrations/0003_migration.py
verification_token/migrations/0004_migration.py
verification_token/migrations/0005_migration.py
verification_token/migrations/__init__.py