Metadata-Version: 1.1
Name: django-verification-token
Version: 0.0.8
Summary: Django library for generation verification toekens.
Home-page: https://github.com/druids/django-verification-token
Author: Lubos Matl
Author-email: matllubos@gmail.com
License: BSD
Keywords: django,verification token
Platform: UNKNOWN
Classifier: Development Status :: 3 - Alpha
Classifier: Framework :: Django
Classifier: Intended Audience :: Developers
Classifier: License :: OSI Approved :: BSD License
Classifier: Operating System :: OS Independent
Classifier: Programming Language :: Python
Classifier: Topic :: Internet :: WWW/HTTP
